pymeme/__init__.py
pymeme-0.1.2.dist-info/LICENSE
pymeme-0.1.2.dist-info/WHEEL
pymeme-0.1.2.dist-info/METADATA
pymeme-0.1.2.dist-info/RECORD
