Metadata-Version: 2.1
Name: pymeme
Version: 0.1.2
Summary: Python and memes.
License: MIT
Author: sangarshanan
Author-email: sangarshanan1998@gmail.com
Maintainer: sangarshanan
Maintainer-email: sangarshanan1998@gmail.com
Requires-Python: >=3.7,<4.0
Classifier: License :: OSI Approved :: MIT License
Classifier: Programming Language :: Python :: 3
Classifier: Programming Language :: Python :: 3.7
Classifier: Programming Language :: Python :: 3.8
Requires-Dist: loguru
Requires-Dist: psutil
